{
  "scheduling": [
    {
      "name": "Class",
      "children": [
        {
          "name": "Room",
          "children": [
            {
              "name": "Site",
              "relation": "Holidays"
            }
          ]
        },
        {
          "name": "Waiting list"
        },
        {
          "name": "Timetable"
        },
        {
          "name": "Tutor",
          "children": [
            {
              "name": "Holidays"
            }
          ]
        }
      ]
    }
  ],
  "automation": [
    {
      "name": "Scripts",
      "children": [
        {
          "name": "Export templates"
        },
        {
          "name": "Import templates"
        },
        {
          "name": "Message templates"
        }
      ]
    },
    {
      "name": "PDF reports",
      "children": [
        {
          "name": "PDF backgrounds"
        }
      ]
    },
    {
      "name": "Integrations"
    }
  ],
  "accounting": [
    {
      "name": "Accounts"
    },
    {
      "name": "Transactions",
      "children": [
        {
          "name": "Invoices"
        },
        {
          "name": "Quotes"
        },
        {
          "name": "Payments in",
          "children": [
            {
              "name": "Batch payment in"
            }
          ]
        },
        {
          "name": "Payments out"
        }
      ]
    },
    {
      "name": "Banking deposits",
      "children": [
        {
          "name": "Deposit banking"
        }
      ]
    },
    {
      "name": "Discounts"
    },
    {
      "name": "Finalise period"
    },
    {
      "name": "Payment types"
    },
    {
      "name": "Tax types"
    },
    {
      "name": "Tutor pay rates",
      "children": [
        {
          "name": "Tutor pay"
        }
      ]
    }
  ],
  "sales": [
    {
      "name": "Quick enrol",
      "children": [
        {
          "name": "Invoices"
        },
        {
          "name": "Payments in",
          "children": [
            {
              "name": "Batch payment in"
            },
            {
              "name": "Sales",
              "children": [
                {
                  "name": "Products"
                },
                {
                  "name": "Voucher types"
                }
              ]
            }
          ]
        },
        {
          "name": "Payments out"
        }
      ]
    },
    {
      "name": "Leads"
    },
    {
      "name": "Messages"
    },
    {
      "name": "Quotes"
    },
    {
      "name": "Waiting lists"
    }
  ],
  "configuration": [
    {
      "name": "Tags",
      "children": [
        {
          "name": "Checklists"
        }
      ]
    },
    {
      "name": "Sites",
      "children": [
        {
          "name": "Rooms"
        }
      ]
    },
    {
      "name": "Preferences",
      "children": [
        {
          "name": "Concession types"
        },
        {
          "name": "Contact relation types"
        },
        {
          "name": "Data collection forms"
        },
        {
          "name": "Payment types"
        },
        {
          "name": "Custom fields"
        },
        {
          "name": "Sellable items relation types"
        },
        {
          "name": "Tutor pay rates"
        },
        {
          "name": "Tax types"
        }
      ]
    },
    {
      "name": "Discounts"
    },
    {
      "name": "Audit logging"
    },
    {
      "name": "Security"
    },
    {
      "name": "Voucher types"
    },
    {
      "name": "Website setup"
    }
  ]
}